top_sgbaird_mwe/__init__.py
top_sgbaird_mwe/sub/LICENSE
top_sgbaird_mwe/sub/README.md
top_sgbaird_mwe/sub/__init__.py
top_sgbaird_mwe-1.0.0.dist-info/LICENSE
top_sgbaird_mwe-1.0.0.dist-info/WHEEL
top_sgbaird_mwe-1.0.0.dist-info/METADATA
top_sgbaird_mwe-1.0.0.dist-info/RECORD
